MANIFEST.in
README.rst
setup.cfg
setup.py
django_croco.egg-info/PKG-INFO
django_croco.egg-info/SOURCES.txt
django_croco.egg-info/dependency_links.txt
django_croco.egg-info/not-zip-safe
django_croco.egg-info/requires.txt
django_croco.egg-info/top_level.txt
djcroco/__init__.py
djcroco/fields.py
djcroco/urls.py
djcroco/views.py
djcroco/templatetags/__init__.py
djcroco/templatetags/croco_tags.py
djcroco/tests/__init__.py
djcroco/tests/models.py
djcroco/tests/tests.py
djcroco/tests/utils.py
test_project/__init__.py
test_project/manage.py
test_project/settings.py
test_project/test_runner.py
test_project/wsgi.py