Metadata-Version: 1.0
Name: django-croco
Version: 1.0.0
Summary: UNKNOWN
Home-page: https://github.com/incuna/django-croco/
Author: Incuna & @mlen108
Author-email: UNKNOWN
License: UNKNOWN
Platform: UNKNOWN
